febiss/__init__.py
febiss/cli/__init__.py
febiss/cli/febiss.py
febiss/cli/febiss_settings.py
febiss/cli/febiss_setup.py
febiss/plotting/__init__.py
febiss/plotting/display.py
febiss/plotting/rdf.py
febiss/utilities/__init__.py
febiss/utilities/distance_functions.py
febiss/utilities/gist.py
febiss/utilities/io_handling.py
febiss/utilities/structures.py
Febiss-0.9.0.dist-info/LICENSE
Febiss-0.9.0.dist-info/METADATA
Febiss-0.9.0.dist-info/WHEEL
Febiss-0.9.0.dist-info/entry_points.txt
Febiss-0.9.0.dist-info/top_level.txt
Febiss-0.9.0.dist-info/RECORD
