Metadata-Version: 2.1
Name: Febiss
Version: 0.9.0
Summary: Tool to ease GIST analysis and display and select FEBISS waters
Home-page: UNKNOWN
Author: Miguel Steiner
Author-email: steiner.mig@gmail.com
License: MIT
Platform: UNKNOWN
Classifier: Programming Language :: Python
Classifier: License :: OSI Approved :: MIT License
Classifier: Natural Language :: English
Classifier: Intended Audience :: Science/Research
Classifier: Topic :: Scientific/Engineering :: Chemistry
Requires-Python: >=3.6
Requires-Dist: certifi (>=2020.12.5)
Requires-Dist: cycler (>=0.10.0)
Requires-Dist: kiwisolver (>=1.3.1)
Requires-Dist: matplotlib (>=3.3.4)
Requires-Dist: numpy (>=1.19.5)
Requires-Dist: Pillow (>=8.1.0)
Requires-Dist: pyparsing (>=2.4.7)
Requires-Dist: python-dateutil (>=2.8.1)
Requires-Dist: PyYAML (>=5.4.1)
Requires-Dist: scipy (>=1.5.4)
Requires-Dist: six (>=1.15.0)
